{
	"nodes": [
		{
			"id": "c_users_utente_documents_still_apps_web_src_components_profile_profile_taste_signature_tsx",
			"label": "profile-taste-signature.tsx",
			"file_type": "code",
			"source_file": "C:\\Users\\Utente\\Documents\\still\\apps\\web\\src\\components\\profile\\profile-taste-signature.tsx",
			"source_location": "L1"
		},
		{
			"id": "profile_profile_taste_signature_profiletastesignature",
			"label": "ProfileTasteSignature()",
			"file_type": "code",
			"source_file": "C:\\Users\\Utente\\Documents\\still\\apps\\web\\src\\components\\profile\\profile-taste-signature.tsx",
			"source_location": "L13"
		}
	],
	"edges": [
		{
			"source": "c_users_utente_documents_still_apps_web_src_components_profile_profile_taste_signature_tsx",
			"target": "c_users_utente_documents_still_packages_ui_src_lib_utils_ts",
			"relation": "imports_from",
			"context": "import",
			"confidence": "EXTRACTED",
			"source_file": "C:\\Users\\Utente\\Documents\\still\\apps\\web\\src\\components\\profile\\profile-taste-signature.tsx",
			"source_location": "L1",
			"weight": 1.0
		},
		{
			"source": "c_users_utente_documents_still_apps_web_src_components_profile_profile_taste_signature_tsx",
			"target": "lib_utils_cn",
			"relation": "imports",
			"context": "import",
			"confidence": "EXTRACTED",
			"source_file": "C:\\Users\\Utente\\Documents\\still\\apps\\web\\src\\components\\profile\\profile-taste-signature.tsx",
			"source_location": "L1",
			"weight": 1.0
		},
		{
			"source": "c_users_utente_documents_still_apps_web_src_components_profile_profile_taste_signature_tsx",
			"target": "c_users_utente_documents_still_apps_web_src_lib_sense_taste_signature_ts",
			"relation": "imports_from",
			"context": "import",
			"confidence": "EXTRACTED",
			"source_file": "C:\\Users\\Utente\\Documents\\still\\apps\\web\\src\\components\\profile\\profile-taste-signature.tsx",
			"source_location": "L3",
			"weight": 1.0
		},
		{
			"source": "c_users_utente_documents_still_apps_web_src_components_profile_profile_taste_signature_tsx",
			"target": "lib_sense_taste_signature_resolvetasteheadline",
			"relation": "imports",
			"context": "import",
			"confidence": "EXTRACTED",
			"source_file": "C:\\Users\\Utente\\Documents\\still\\apps\\web\\src\\components\\profile\\profile-taste-signature.tsx",
			"source_location": "L3",
			"weight": 1.0
		},
		{
			"source": "c_users_utente_documents_still_apps_web_src_components_profile_profile_taste_signature_tsx",
			"target": "lib_sense_taste_signature_tastearchetypelabel",
			"relation": "imports",
			"context": "import",
			"confidence": "EXTRACTED",
			"source_file": "C:\\Users\\Utente\\Documents\\still\\apps\\web\\src\\components\\profile\\profile-taste-signature.tsx",
			"source_location": "L3",
			"weight": 1.0
		},
		{
			"source": "c_users_utente_documents_still_apps_web_src_components_profile_profile_taste_signature_tsx",
			"target": "lib_sense_taste_signature_tasteperspective",
			"relation": "imports",
			"context": "import",
			"confidence": "EXTRACTED",
			"source_file": "C:\\Users\\Utente\\Documents\\still\\apps\\web\\src\\components\\profile\\profile-taste-signature.tsx",
			"source_location": "L3",
			"weight": 1.0
		},
		{
			"source": "c_users_utente_documents_still_apps_web_src_components_profile_profile_taste_signature_tsx",
			"target": "lib_sense_taste_signature_tastesignaturejson",
			"relation": "imports",
			"context": "import",
			"confidence": "EXTRACTED",
			"source_file": "C:\\Users\\Utente\\Documents\\still\\apps\\web\\src\\components\\profile\\profile-taste-signature.tsx",
			"source_location": "L3",
			"weight": 1.0
		},
		{
			"source": "c_users_utente_documents_still_apps_web_src_components_profile_profile_taste_signature_tsx",
			"target": "profile_profile_taste_signature_profiletastesignature",
			"relation": "contains",
			"confidence": "EXTRACTED",
			"source_file": "C:\\Users\\Utente\\Documents\\still\\apps\\web\\src\\components\\profile\\profile-taste-signature.tsx",
			"source_location": "L13",
			"weight": 1.0
		}
	],
	"raw_calls": [
		{
			"caller_nid": "profile_profile_taste_signature_profiletastesignature",
			"callee": "resolveTasteHeadline",
			"is_member_call": false,
			"source_file": "C:\\Users\\Utente\\Documents\\still\\apps\\web\\src\\components\\profile\\profile-taste-signature.tsx",
			"source_location": "L23"
		},
		{
			"caller_nid": "profile_profile_taste_signature_profiletastesignature",
			"callee": "cn",
			"is_member_call": false,
			"source_file": "C:\\Users\\Utente\\Documents\\still\\apps\\web\\src\\components\\profile\\profile-taste-signature.tsx",
			"source_location": "L43"
		},
		{
			"caller_nid": "profile_profile_taste_signature_profiletastesignature",
			"callee": "cn",
			"is_member_call": false,
			"source_file": "C:\\Users\\Utente\\Documents\\still\\apps\\web\\src\\components\\profile\\profile-taste-signature.tsx",
			"source_location": "L53"
		},
		{
			"caller_nid": "profile_profile_taste_signature_profiletastesignature",
			"callee": "tasteArchetypeLabel",
			"is_member_call": false,
			"source_file": "C:\\Users\\Utente\\Documents\\still\\apps\\web\\src\\components\\profile\\profile-taste-signature.tsx",
			"source_location": "L62"
		}
	]
}
