{
	"nodes": [
		{
			"id": "c_users_utente_documents_still_apps_web_src_lib_list_reorder_live_sync_ts",
			"label": "list-reorder-live-sync.ts",
			"file_type": "code",
			"source_file": "C:\\Users\\Utente\\Documents\\still\\apps\\web\\src\\lib\\list-reorder-live-sync.ts",
			"source_location": "L1"
		},
		{
			"id": "lib_list_reorder_live_sync_sortfilmrowsbyitemids",
			"label": "sortFilmRowsByItemIds()",
			"file_type": "code",
			"source_file": "C:\\Users\\Utente\\Documents\\still\\apps\\web\\src\\lib\\list-reorder-live-sync.ts",
			"source_location": "L6"
		},
		{
			"id": "lib_list_reorder_live_sync_filmroworderkey",
			"label": "filmRowOrderKey()",
			"file_type": "code",
			"source_file": "C:\\Users\\Utente\\Documents\\still\\apps\\web\\src\\lib\\list-reorder-live-sync.ts",
			"source_location": "L19"
		},
		{
			"id": "lib_list_reorder_live_sync_broadcastlistreordered",
			"label": "broadcastListReordered()",
			"file_type": "code",
			"source_file": "C:\\Users\\Utente\\Documents\\still\\apps\\web\\src\\lib\\list-reorder-live-sync.ts",
			"source_location": "L26"
		},
		{
			"id": "lib_list_reorder_live_sync_subscribelistreorderedbroadcast",
			"label": "subscribeListReorderedBroadcast()",
			"file_type": "code",
			"source_file": "C:\\Users\\Utente\\Documents\\still\\apps\\web\\src\\lib\\list-reorder-live-sync.ts",
			"source_location": "L37"
		}
	],
	"edges": [
		{
			"source": "c_users_utente_documents_still_apps_web_src_lib_list_reorder_live_sync_ts",
			"target": "c_users_utente_documents_still_apps_web_src_components_list_list_detail_films_grid_tsx",
			"relation": "imports_from",
			"context": "import",
			"confidence": "EXTRACTED",
			"source_file": "C:\\Users\\Utente\\Documents\\still\\apps\\web\\src\\lib\\list-reorder-live-sync.ts",
			"source_location": "L1",
			"weight": 1.0
		},
		{
			"source": "c_users_utente_documents_still_apps_web_src_lib_list_reorder_live_sync_ts",
			"target": "list_list_detail_films_grid_listdetailfilmrow",
			"relation": "imports",
			"context": "import",
			"confidence": "EXTRACTED",
			"source_file": "C:\\Users\\Utente\\Documents\\still\\apps\\web\\src\\lib\\list-reorder-live-sync.ts",
			"source_location": "L1",
			"weight": 1.0
		},
		{
			"source": "c_users_utente_documents_still_apps_web_src_lib_list_reorder_live_sync_ts",
			"target": "lib_list_reorder_live_sync_sortfilmrowsbyitemids",
			"relation": "contains",
			"confidence": "EXTRACTED",
			"source_file": "C:\\Users\\Utente\\Documents\\still\\apps\\web\\src\\lib\\list-reorder-live-sync.ts",
			"source_location": "L6",
			"weight": 1.0
		},
		{
			"source": "c_users_utente_documents_still_apps_web_src_lib_list_reorder_live_sync_ts",
			"target": "lib_list_reorder_live_sync_filmroworderkey",
			"relation": "contains",
			"confidence": "EXTRACTED",
			"source_file": "C:\\Users\\Utente\\Documents\\still\\apps\\web\\src\\lib\\list-reorder-live-sync.ts",
			"source_location": "L19",
			"weight": 1.0
		},
		{
			"source": "c_users_utente_documents_still_apps_web_src_lib_list_reorder_live_sync_ts",
			"target": "lib_list_reorder_live_sync_broadcastlistreordered",
			"relation": "contains",
			"confidence": "EXTRACTED",
			"source_file": "C:\\Users\\Utente\\Documents\\still\\apps\\web\\src\\lib\\list-reorder-live-sync.ts",
			"source_location": "L26",
			"weight": 1.0
		},
		{
			"source": "c_users_utente_documents_still_apps_web_src_lib_list_reorder_live_sync_ts",
			"target": "lib_list_reorder_live_sync_subscribelistreorderedbroadcast",
			"relation": "contains",
			"confidence": "EXTRACTED",
			"source_file": "C:\\Users\\Utente\\Documents\\still\\apps\\web\\src\\lib\\list-reorder-live-sync.ts",
			"source_location": "L37",
			"weight": 1.0
		}
	],
	"raw_calls": [
		{
			"caller_nid": "lib_list_reorder_live_sync_sortfilmrowsbyitemids",
			"callee": "map",
			"is_member_call": true,
			"source_file": "C:\\Users\\Utente\\Documents\\still\\apps\\web\\src\\lib\\list-reorder-live-sync.ts",
			"source_location": "L10"
		},
		{
			"caller_nid": "lib_list_reorder_live_sync_sortfilmrowsbyitemids",
			"callee": "sort",
			"is_member_call": true,
			"source_file": "C:\\Users\\Utente\\Documents\\still\\apps\\web\\src\\lib\\list-reorder-live-sync.ts",
			"source_location": "L11"
		},
		{
			"caller_nid": "lib_list_reorder_live_sync_filmroworderkey",
			"callee": "join",
			"is_member_call": true,
			"source_file": "C:\\Users\\Utente\\Documents\\still\\apps\\web\\src\\lib\\list-reorder-live-sync.ts",
			"source_location": "L22"
		},
		{
			"caller_nid": "lib_list_reorder_live_sync_filmroworderkey",
			"callee": "map",
			"is_member_call": true,
			"source_file": "C:\\Users\\Utente\\Documents\\still\\apps\\web\\src\\lib\\list-reorder-live-sync.ts",
			"source_location": "L22"
		},
		{
			"caller_nid": "lib_list_reorder_live_sync_broadcastlistreordered",
			"callee": "postMessage",
			"is_member_call": true,
			"source_file": "C:\\Users\\Utente\\Documents\\still\\apps\\web\\src\\lib\\list-reorder-live-sync.ts",
			"source_location": "L32"
		},
		{
			"caller_nid": "lib_list_reorder_live_sync_broadcastlistreordered",
			"callee": "close",
			"is_member_call": true,
			"source_file": "C:\\Users\\Utente\\Documents\\still\\apps\\web\\src\\lib\\list-reorder-live-sync.ts",
			"source_location": "L33"
		}
	]
}
